itkwasm_compare_images/__init__.py
itkwasm_compare_images/_version.py
itkwasm_compare_images/compare_double_images.py
itkwasm_compare_images/compare_double_images_async.py
itkwasm_compare_images/compare_images.py
itkwasm_compare_images/compare_images_async.py
itkwasm_compare_images/vector_magnitude.py
itkwasm_compare_images/vector_magnitude_async.py
itkwasm_compare_images-5.4.1.dist-info/METADATA
itkwasm_compare_images-5.4.1.dist-info/WHEEL
itkwasm_compare_images-5.4.1.dist-info/RECORD
