Metadata-Version: 2.3
Name: itkwasm-compare-images
Version: 5.4.1
Summary: Compare images with a tolerance for regression testing.
Project-URL: Home, https://github.com/InsightSoftwareConsortium/ITK-Wasm
Project-URL: Source, https://github.com/InsightSoftwareConsortium/ITK-Wasm
Keywords: emscripten,itkwasm,wasi,webassembly
Classifier: Development Status :: 4 - Beta
Classifier: Environment :: WebAssembly
Classifier: Environment :: WebAssembly :: Emscripten
Classifier: Environment :: WebAssembly :: WASI
Classifier: Intended Audience :: Developers
Classifier: Intended Audience :: Science/Research
Classifier: License :: OSI Approved :: Apache Software License
Classifier: Programming Language :: C++
Classifier: Programming Language :: Python
Classifier: Programming Language :: Python :: 3
Classifier: Programming Language :: Python :: 3.8
Classifier: Programming Language :: Python :: 3.9
Classifier: Programming Language :: Python :: 3.10
Classifier: Programming Language :: Python :: 3.11
Requires-Python: >=3.8
Requires-Dist: itkwasm-compare-images-emscripten>=1.0.1; sys_platform == 'emscripten'
Requires-Dist: itkwasm-compare-images-wasi>=1.0.1; sys_platform != 'emscripten'
Requires-Dist: itkwasm>=1.0.b171
